crisprbuilder_tb/REP/sequences/__init__.py
crisprbuilder_tb/__init__.py
crisprbuilder_tb/__main__.py
crisprbuilder_tb/bdd.py
crisprbuilder_tb/data/1_3882_SORTED.xls
crisprbuilder_tb/data/Brynildsrud_Dataset_S1.xls
crisprbuilder_tb/data/NC_000962.3.txt
crisprbuilder_tb/data/lineage.csv
crisprbuilder_tb/data/spoligo_new.fasta
crisprbuilder_tb/data/spoligo_old.fasta
crisprbuilder_tb/data/spoligo_vitro.fasta
crisprbuilder_tb/data/spoligo_vitro_new.fasta
crisprbuilder_tb/doc/.ipynb_checkpoints/M2_projet-checkpoint.ipynb
crisprbuilder_tb/doc/.ipynb_checkpoints/crisprbuilder-tb-checkpoint.ipynb
crisprbuilder_tb/doc/.ipynb_checkpoints/crisprbuilder_tb-checkpoint.ipynb
crisprbuilder_tb/doc/LICENSE
crisprbuilder_tb/doc/crisprbuilder_tb.ipynb
crisprbuilder_tb/doc/femto.png
crisprbuilder_tb/doc/rep_crispr.png
crisprbuilder_tb/doc/selection.png
crisprbuilder_tb/fonctions.py
crisprbuilder_tb/tmp/__init__.py
crisprbuilder_tb/unittestmain.py
crisprbuilder_tb-0.1.47.dist-info/WHEEL
crisprbuilder_tb-0.1.47.dist-info/METADATA
crisprbuilder_tb-0.1.47.dist-info/RECORD
