Metadata-Version: 2.1
Name: crisprbuilder-tb
Version: 0.1.47
Summary: Collect and annotate Mycobacterium tuberculosis WGS data for CRISPR investigations.
Home-page: https://github.com/stephane-robin/crisprbuilder_tb.git
License: MIT
Keywords: tuberculosis,CRISPR
Author: stephane-robin
Author-email: robin.stephane@outlook.com
Requires-Python: >=3.6,<4.0
Classifier: License :: OSI Approved :: MIT License
Classifier: Programming Language :: Python :: 3
Classifier: Programming Language :: Python :: 3.6
Classifier: Programming Language :: Python :: 3.7
Classifier: Programming Language :: Python :: 3.8
Requires-Dist: biopython (>=1.77,<2.0)
Requires-Dist: parallel-fastq-dump (>=0.6.5,<0.7.0)
Requires-Dist: xlrd (>=1.2.0,<2.0.0)
Requires-Dist: xmltodict (>=0.12.0,<0.13.0)
Project-URL: Repository, https://github.com/stephane-robin/crisprbuilder_tb.git
